vements/__init__.py
vements/__main__.py
vements/api.py
vements/client.py
vements/config.py
vements/types.py
vements-0.0.5.dist-info/METADATA
vements-0.0.5.dist-info/WHEEL
vements-0.0.5.dist-info/RECORD
