Metadata-Version: 2.1
Name: vements
Version: 0.0.5
Summary: Achievements and Scoreboards for Everyone
Project-URL: Homepage, https://github.com/vements/client-py
Project-URL: Bug Tracker, https://github.com/vements/client-py/issues
Author-email: Vements Support <support@vements.io>
Classifier: License :: OSI Approved :: MIT License
Classifier: Operating System :: OS Independent
Classifier: Programming Language :: Python :: 3
Requires-Python: >=3.7
